powerengine/__init__.py
powerengine-1.0.0.dist-info/LICENSE
powerengine-1.0.0.dist-info/METADATA
powerengine-1.0.0.dist-info/WHEEL
powerengine-1.0.0.dist-info/top_level.txt
powerengine-1.0.0.dist-info/RECORD
