Metadata-Version: 2.1
Name: powerengine
Version: 1.0.0
Summary: A library which calculates signals and electricity.
Author-email: Aarav Malani <aarav.malani@gmail.com>
Project-URL: Homepage, https://github.com/AaravMalani/powerengine
Project-URL: Bug Tracker, https://github.com/AaravMalani/powerengine/issues
Classifier: Programming Language :: Python :: 3
Classifier: License :: OSI Approved :: MIT License
Classifier: Operating System :: OS Independent
Requires-Python: >=3.6
License-File: LICENSE
